{
  "url": "https://www.alibaba.com/product-detail/Original-Japan-Used-Caterpillar-Excavator-320d2l_1601423040295.html",
  "product_info": {
    "title": "Original Japan Used Caterpillar Excavator 320d2l, Cat 320 320d 320gc 320dl High Quality and Cost-effective Hot Sale",
    "price": null
  },
  "attributes": {
    "Industry-specific attributes": {
      "Operating Weight": "21115kg",
      "Bucket capacity": "0.8m3",
      "Engine Brand": "others",
      "Power": "75KW",
      "Working hours": "2001-4000"
    },
    "Other attributes": {
      "Machine Weight": "20000 KG",
      "Hydraulic Cylinder Brand": "cat",
      "Hydraulic Pump Brand": "cat",
      "Hydraulic Valve Brand": "cat",
      "Core Components": "Pump",
      "Year": "2016",
      "Place of Origin": "Japan",
      "Machinery Test Report": "Not Available",
      "Video outgoing-inspection": "Provided",
      "Bucketcapacity": "1.5m3",
      "ApplicableIndustries": "Constructionworks",
      "AfterWarranty Service": "No service",
      "LocalService Location": "Japan",
      "Condition": "Used",
      "Make": "CATERPILLAR",
      "MovingType": "Crawler Excavator",
      "Warranty": "Unavailable",
      "MarketingType": "Hot Product 2019",
      "Warrantyof core components": "Not Available"
    }
  }
}